Metadata-Version: 2.1
Name: ws-gfdl
Version: 1.1.0
Summary: Beta Package to implement WebSocket API of Global Datafeeds
Author: Global Datafeeds
Author-email: Global Datafeeds <developer@globaldatafeeds.in>
License: Copyright (c) 2018 The Python Packaging Authority        
Keywords: python,first package
Classifier: Programming Language :: Python :: 3
Classifier: License :: OSI Approved :: MIT License
Classifier: Operating System :: OS Independent
Requires-Python: >=3.9
License-File: LICENSE
Requires-Dist: websockets
